thermodynamic_truth/__init__.py
thermodynamic_truth/cli/__init__.py
thermodynamic_truth/cli/benchmark.py
thermodynamic_truth/cli/client.py
thermodynamic_truth/cli/node.py
thermodynamic_truth/core/__init__.py
thermodynamic_truth/core/annealing.py
thermodynamic_truth/core/pow.py
thermodynamic_truth/core/protocol.py
thermodynamic_truth/core/state.py
thermodynamic_truth/network/__init__.py
thermodynamic_truth/network/client.py
thermodynamic_truth/network/server.py
thermodynamic_truth/network/thermo_protocol.proto
thermodynamic_truth/network/thermo_protocol_pb2.py
thermodynamic_truth/network/thermo_protocol_pb2_grpc.py
thermodynamic_truth-1.1.0.dist-info/licenses/LICENSE
thermodynamic_truth-1.1.0.dist-info/METADATA
thermodynamic_truth-1.1.0.dist-info/WHEEL
thermodynamic_truth-1.1.0.dist-info/entry_points.txt
thermodynamic_truth-1.1.0.dist-info/top_level.txt
thermodynamic_truth-1.1.0.dist-info/RECORD
