Metadata-Version: 2.4
Name: thermodynamic-truth
Version: 1.1.0
Summary: Thermodynamic Consensus Protocol - Byzantine Fault Tolerant consensus using statistical mechanics
Home-page: https://github.com/Kuonirad/thermo-truth-proto
Author: Kevin KULL
Author-email: Kevin KULL <info@thermodynamic-truth.org>
License: Apache-2.0
Classifier: Development Status :: 3 - Alpha
Classifier: Intended Audience :: Developers
Classifier: License :: OSI Approved :: Apache Software License
Classifier: Programming Language :: Python :: 3
Classifier: Programming Language :: Python :: 3.9
Classifier: Programming Language :: Python :: 3.10
Classifier: Programming Language :: Python :: 3.11
Requires-Python: >=3.8
License-File: LICENSE
Requires-Dist: numpy>=1.24.0
Requires-Dist: grpcio>=1.60.0
Requires-Dist: grpcio-tools>=1.60.0
Requires-Dist: protobuf>=4.25.0
Provides-Extra: dev
Requires-Dist: pytest>=7.4.0; extra == "dev"
Requires-Dist: pytest-cov>=4.1.0; extra == "dev"
Requires-Dist: black>=23.12.0; extra == "dev"
Requires-Dist: flake8>=7.0.0; extra == "dev"
Requires-Dist: mypy>=1.8.0; extra == "dev"
Requires-Dist: pre-commit>=3.6.0; extra == "dev"
Provides-Extra: viz
Requires-Dist: matplotlib>=3.8.0; extra == "viz"
Dynamic: author
Dynamic: home-page
Dynamic: license-file
Dynamic: requires-python
